fastapi_jsonapi/VERSION
fastapi_jsonapi/__init__.py
fastapi_jsonapi/common.py
fastapi_jsonapi/data_typing.py
fastapi_jsonapi/py.typed
fastapi_jsonapi/querystring.py
fastapi_jsonapi/schema.py
fastapi_jsonapi/schema_base.py
fastapi_jsonapi/schema_builder.py
fastapi_jsonapi/signature.py
fastapi_jsonapi/validation_utils.py
fastapi_jsonapi/api/__init__.py
fastapi_jsonapi/api/application_builder.py
fastapi_jsonapi/api/endpoint_builder.py
fastapi_jsonapi/api/schemas.py
fastapi_jsonapi/atomic/__init__.py
fastapi_jsonapi/atomic/atomic.py
fastapi_jsonapi/atomic/atomic_handler.py
fastapi_jsonapi/atomic/prepared_atomic_operation.py
fastapi_jsonapi/atomic/schemas.py
fastapi_jsonapi/data_layers/__init__.py
fastapi_jsonapi/data_layers/base.py
fastapi_jsonapi/data_layers/fields/__init__.py
fastapi_jsonapi/data_layers/fields/enums.py
fastapi_jsonapi/data_layers/fields/mixins.py
fastapi_jsonapi/data_layers/sqla/__init__.py
fastapi_jsonapi/data_layers/sqla/base_model.py
fastapi_jsonapi/data_layers/sqla/orm.py
fastapi_jsonapi/data_layers/sqla/query_building.py
fastapi_jsonapi/exceptions/__init__.py
fastapi_jsonapi/exceptions/base.py
fastapi_jsonapi/exceptions/handlers.py
fastapi_jsonapi/exceptions/json_api.py
fastapi_jsonapi/misc/__init__.py
fastapi_jsonapi/misc/sqla/__init__.py
fastapi_jsonapi/misc/sqla/generics/__init__.py
fastapi_jsonapi/misc/sqla/generics/base.py
fastapi_jsonapi/storages/__init__.py
fastapi_jsonapi/storages/models_storage.py
fastapi_jsonapi/storages/schemas_storage.py
fastapi_jsonapi/storages/views_storage.py
fastapi_jsonapi/types_metadata/__init__.py
fastapi_jsonapi/types_metadata/client_can_set_id.py
fastapi_jsonapi/types_metadata/custom_filter_sql.py
fastapi_jsonapi/types_metadata/custom_sort_sql.py
fastapi_jsonapi/types_metadata/relationship_info.py
fastapi_jsonapi/utils/__init__.py
fastapi_jsonapi/utils/dependency_helper.py
fastapi_jsonapi/utils/exceptions.py
fastapi_jsonapi/utils/metadata_instance_search.py
fastapi_jsonapi/views/__init__.py
fastapi_jsonapi-3.0.0.dist-info/METADATA
fastapi_jsonapi-3.0.0.dist-info/WHEEL
fastapi_jsonapi-3.0.0.dist-info/licenses/LICENSE
fastapi_jsonapi-3.0.0.dist-info/RECORD
