Metadata-Version: 2.4
Name: FastAPI-JSONAPI
Version: 3.0.0
Summary: FastAPI extension to create REST web api according to JSON:API 1.0 specification with FastAPI, Pydantic and data provider (SQLAlchemy)
Project-URL: Documentation, https://fastapi-jsonapi.readthedocs.io/
Project-URL: Source, https://github.com/mts-ai/FastAPI-JSONAPI
Author-email: Aleksey Nekrasov <a.nekrasov@mts.ai>, Suren Khorenyan <s.khorenyan@mts.ai>, German Bernadskiy <german11235813@gmail.com>
License-Expression: MIT
License-File: LICENSE
Keywords: fastapi,json:api,jsonapi
Classifier: Development Status :: 5 - Production/Stable
Classifier: Operating System :: OS Independent
Classifier: Programming Language :: Python :: 3.9
Classifier: Programming Language :: Python :: 3.10
Classifier: Programming Language :: Python :: 3.11
Classifier: Programming Language :: Python :: 3.12
Classifier: Topic :: Utilities
Requires-Dist: fastapi>=0.112.3
Requires-Dist: orjson>=3.10.0
Requires-Dist: pydantic>=2.6.0
Provides-Extra: all
Requires-Dist: pytest; extra == 'all'
Requires-Dist: sphinx; extra == 'all'
Requires-Dist: sqlalchemy[asyncio]>=2.0.26; extra == 'all'
Requires-Dist: uvicorn>=0.18.2; extra == 'all'
Provides-Extra: docs
Requires-Dist: sphinx; extra == 'docs'
Provides-Extra: sqlalchemy
Requires-Dist: sqlalchemy[asyncio]>=2.0.26; extra == 'sqlalchemy'
Provides-Extra: tests
Requires-Dist: pytest; extra == 'tests'
Provides-Extra: uvicorn
Requires-Dist: uvicorn>=0.18.2; extra == 'uvicorn'
